{
  "apiVersion": "vlabs",
  "properties": {
    "orchestratorProfile": {
      "orchestratorType": "DCOS"
    },
    "masterProfile": {
      "count": 1,
      "dnsPrefix": "",
      "vmSize": "Standard_D2s_v3",
      "OSDiskSizeGB": 200
    },
    "agentPoolProfiles": [
      {
        "name": "agentpublic",
        "count": 3,
        "vmSize": "Standard_D2s_v3",
        "OSDiskSizeGB": 200,
        "AvailabilityProfile": "VirtualMachineScaleSets",
        "storageProfile": "ManagedDisks",
        "dnsPrefix": "",
        "ports": [
          80,
          443,
          8080
        ]
      }
    ],
    "linuxProfile": {
      "adminUsername": "azureuser",
      "ssh": {
        "publicKeys": [
          {
            "keyData": ""
          }
        ]
      }
    }
  }
}